{"title":"Applications","description":"Gaskets By Application","createdAt":"2022-04-19T01:54:06.556Z","updatedAt":"2022-04-19T01:59:12.735Z","seo":{"id":1744,"title":"Applications","description":"Gaskets By Application","image":{}},"blocks":[{"id":35,"__component":"block.collection","collectionType":"applications","title":null,"cardSettings":{"id":35,"style":null,"classes":{"card":"col-span-12 md:col-span6"},"showMoreLinks":true,"showExcerpt":true},"collectionSettings":{"id":36,"limit":12,"sort":"order","infiniteScroll":true,"updateUrl":true,"filters":null,"searchBar":false,"loadingMore":"infiniteScroll","buttonLink":null,"buttonText":null},"blockSettings":null}],"pageSettings":null,"id":1}