{"title":"Datasheets","description":null,"createdAt":"2022-04-19T01:03:45.431Z","updatedAt":"2022-04-19T01:59:12.808Z","seo":{"id":1750,"title":"Datasheets","description":null,"image":{}},"blocks":[{"id":40,"__component":"block.collection","collectionType":"datasheets","title":null,"cardSettings":{"id":40,"style":null,"classes":{"card":"datasheet col-span-12 sm:col-span-6"},"showMoreLinks":true,"showExcerpt":null},"collectionSettings":{"id":40,"limit":12,"sort":"title","infiniteScroll":true,"updateUrl":true,"filters":null,"searchBar":false,"loadingMore":"infiniteScroll","buttonLink":null,"buttonText":null},"blockSettings":{"id":29,"classes":null,"sidebar":false}}],"pageSettings":null,"id":1}