{"title":"EMI Shielding Gaskets","slug":"emi-shielding-gaskets","type":"gasket","collectionType":"gaskets","content":"<p>SRP has been providing custom converted EMI Shielding gaskets and seals to various industries since 1951. We exceed customer expectations through exceptional customer service, quality manufacturing, competitive pricing and on-time delivery. EMI Shielding gaskets and seals can be custom fabricated to your exact specifications and requirements.</p>","order":null,"description":"EMI Shielding gaskets and seals can be custom fabricated to your exact specifications and requirements. Contact us today!","createdAt":"2022-04-15T19:58:10.337Z","updatedAt":"2022-04-16T01:19:33.438Z","publishedAt":"2021-03-05T23:30:29.000Z","media":{"id":182,"name":"IMG_0410_127d46f15b.jpg","alternativeText":"","caption":"uploads/IMG_0410_127d46f15b.jpg","width":1220,"height":382,"formats":{"large":{"ext":".jpg","url":"https://res.cloudinary.com/srp-media/image/upload/v1650056994/large_IMG_0410_127d46f15b_d82a3401c5.jpg","hash":"large_IMG_0410_127d46f15b_d82a3401c5","mime":"image/jpeg","name":"large_IMG_0410_127d46f15b.jpg","path":null,"size":76.86,"width":1000,"height":313,"provider_metadata":{"public_id":"large_IMG_0410_127d46f15b_d82a3401c5","resource_type":"image"}},"small":{"ext":".jpg","url":"https://res.cloudinary.com/srp-media/image/upload/v1650056995/small_IMG_0410_127d46f15b_d82a3401c5.jpg","hash":"small_IMG_0410_127d46f15b_d82a3401c5","mime":"image/jpeg","name":"small_IMG_0410_127d46f15b.jpg","path":null,"size":21.91,"width":500,"height":157,"provider_metadata":{"public_id":"small_IMG_0410_127d46f15b_d82a3401c5","resource_type":"image"}},"medium":{"ext":".jpg","url":"https://res.cloudinary.com/srp-media/image/upload/v1650056995/medium_IMG_0410_127d46f15b_d82a3401c5.jpg","hash":"medium_IMG_0410_127d46f15b_d82a3401c5","mime":"image/jpeg","name":"medium_IMG_0410_127d46f15b.jpg","path":null,"size":47.44,"width":750,"height":235,"provider_metadata":{"public_id":"medium_IMG_0410_127d46f15b_d82a3401c5","resource_type":"image"}},"thumbnail":{"ext":".jpg","url":"https://res.cloudinary.com/srp-media/image/upload/v1650056994/thumbnail_IMG_0410_127d46f15b_d82a3401c5.jpg","hash":"thumbnail_IMG_0410_127d46f15b_d82a3401c5","mime":"image/jpeg","name":"thumbnail_IMG_0410_127d46f15b.jpg","path":null,"size":7.23,"width":245,"height":77,"provider_metadata":{"public_id":"thumbnail_IMG_0410_127d46f15b_d82a3401c5","resource_type":"image"}}},"hash":"IMG_0410_127d46f15b_d82a3401c5","ext":".jpg","mime":"image/jpeg","size":77.27,"url":"https://res.cloudinary.com/srp-media/image/upload/v1650056994/IMG_0410_127d46f15b_d82a3401c5.jpg","previewUrl":null,"provider":"cloudinary","provider_metadata":{"public_id":"IMG_0410_127d46f15b_d82a3401c5","resource_type":"image"},"createdAt":"2022-04-15T21:09:55.752Z","updatedAt":"2022-04-15T21:09:55.752Z"},"seo":{"id":784,"title":"EMI Shielding Gaskets","description":"EMI Shielding gaskets and seals can be custom fabricated to your exact specifications and requirements. Contact us today!","image":{"id":182,"name":"IMG_0410_127d46f15b.jpg","alternativeText":"","caption":"uploads/IMG_0410_127d46f15b.jpg","width":1220,"height":382,"formats":{"large":{"ext":".jpg","url":"https://res.cloudinary.com/srp-media/image/upload/v1650056994/large_IMG_0410_127d46f15b_d82a3401c5.jpg","hash":"large_IMG_0410_127d46f15b_d82a3401c5","mime":"image/jpeg","name":"large_IMG_0410_127d46f15b.jpg","path":null,"size":76.86,"width":1000,"height":313,"provider_metadata":{"public_id":"large_IMG_0410_127d46f15b_d82a3401c5","resource_type":"image"}},"small":{"ext":".jpg","url":"https://res.cloudinary.com/srp-media/image/upload/v1650056995/small_IMG_0410_127d46f15b_d82a3401c5.jpg","hash":"small_IMG_0410_127d46f15b_d82a3401c5","mime":"image/jpeg","name":"small_IMG_0410_127d46f15b.jpg","path":null,"size":21.91,"width":500,"height":157,"provider_metadata":{"public_id":"small_IMG_0410_127d46f15b_d82a3401c5","resource_type":"image"}},"medium":{"ext":".jpg","url":"https://res.cloudinary.com/srp-media/image/upload/v1650056995/medium_IMG_0410_127d46f15b_d82a3401c5.jpg","hash":"medium_IMG_0410_127d46f15b_d82a3401c5","mime":"image/jpeg","name":"medium_IMG_0410_127d46f15b.jpg","path":null,"size":47.44,"width":750,"height":235,"provider_metadata":{"public_id":"medium_IMG_0410_127d46f15b_d82a3401c5","resource_type":"image"}},"thumbnail":{"ext":".jpg","url":"https://res.cloudinary.com/srp-media/image/upload/v1650056994/thumbnail_IMG_0410_127d46f15b_d82a3401c5.jpg","hash":"thumbnail_IMG_0410_127d46f15b_d82a3401c5","mime":"image/jpeg","name":"thumbnail_IMG_0410_127d46f15b.jpg","path":null,"size":7.23,"width":245,"height":77,"provider_metadata":{"public_id":"thumbnail_IMG_0410_127d46f15b_d82a3401c5","resource_type":"image"}}},"hash":"IMG_0410_127d46f15b_d82a3401c5","ext":".jpg","mime":"image/jpeg","size":77.27,"url":"https://res.cloudinary.com/srp-media/image/upload/v1650056994/IMG_0410_127d46f15b_d82a3401c5.jpg","previewUrl":null,"provider":"cloudinary","provider_metadata":{"public_id":"IMG_0410_127d46f15b_d82a3401c5","resource_type":"image"},"createdAt":"2022-04-15T21:09:55.752Z","updatedAt":"2022-04-15T21:09:55.752Z"}},"blocks":[{"id":914,"__component":"block.content","content":"<ul><li>Tensile Strength</li><li>Tear Resistance</li><li>Thermal Stability/Conductivity</li><li>Particle Filled Silicones</li></ul>","title":"EMI Shielding Gasket Features","blockSettings":null},{"id":917,"__component":"block.content","content":"<ul>\n<li>Voltage Endurance</li>\n<li>Thermal Conductivity</li>\n<li>Excellent dielectric strength shields against electrical surges</li>\n<li>Mechanical Toughness</li>\n</ul>","title":"Benefits","blockSettings":null},{"id":915,"__component":"block.content","content":"<ul><li>3M ThermaVolt Insulation Paper</li><li>BISCO EC-2130 Silicone EMI Shields</li><li>Nomex Type 410</li><li>Formex Polypropylene</li><li>SSP EMI / RFI Conductive Silicones\n            </li></ul>","title":"Common EMI Shielding Gasket Materials","blockSettings":null},{"id":916,"__component":"block.content","content":"<ul><li>EMI Shielding\n            </li><li>Appliance Controls</li><li>Electronic Devices</li><li>Automotive Controls</li><li>Electrical Insulation</li><li>Circuit Breakers</li></ul>","title":"Applications","blockSettings":null}],"pageSettings":null,"applications":[],"materials":[],"suppliers":[],"id":53}